django_requesting_os_analyzer/.DS_Store
django_requesting_os_analyzer/__init__.py
django_requesting_os_analyzer/admin.py
django_requesting_os_analyzer/apps.py
django_requesting_os_analyzer/middleware.py
django_requesting_os_analyzer/migrations/.DS_Store
django_requesting_os_analyzer/migrations/__init__.py
django_requesting_os_analyzer/models.py
django_requesting_os_analyzer/templates/.DS_Store
django_requesting_os_analyzer/templates/admin/.DS_Store
django_requesting_os_analyzer/templates/admin/django_requesting_os_analyzer/.DS_Store
django_requesting_os_analyzer/templates/admin/django_requesting_os_analyzer/stat/change_list.html
django_requesting_os_analyzer/tests.py
django_requesting_os_analyzer/views.py
django_requesting_os_analyzer-0.1.4.dist-info/WHEEL
django_requesting_os_analyzer-0.1.4.dist-info/METADATA
django_requesting_os_analyzer-0.1.4.dist-info/RECORD
