Metadata-Version: 2.1
Name: django-requesting-os-analyzer
Version: 0.1.4
Summary: Counts the number of the requests coming from various os.
License: MIT
Keywords: count,request,os,analyzer,django,django requesting os analyzer
Author: hassan-shahzad
Author-email: hassanshahzadthegeek@gmail.com
Requires-Python: >=3.7,<4.0
Classifier: License :: OSI Approved :: MIT License
Classifier: Programming Language :: Python :: 3
Classifier: Programming Language :: Python :: 3.10
Classifier: Programming Language :: Python :: 3.7
Classifier: Programming Language :: Python :: 3.8
Classifier: Programming Language :: Python :: 3.9
Requires-Dist: Django (>3.2)
